reche/__init__.py
reche/cache.py
reche/utils.py
reche-0.1.1.dist-info/METADATA
reche-0.1.1.dist-info/WHEEL
reche-0.1.1.dist-info/top_level.txt
reche-0.1.1.dist-info/RECORD
