Metadata-Version: 2.2
Name: reche
Version: 0.1.1
Summary: Reche (Redis Cache) is a Python library that provides a simple interface for caching data in Redis.
Requires-Python: >=3.10
Requires-Dist: redis>=5.2.1
